foldcomp_bin
mDeepFRI/pdb.py
mDeepFRI/pipeline.py
mDeepFRI/contact_map_utils.cpython-310-x86_64-linux-gnu.so
mDeepFRI/bio_utils.py
mDeepFRI/database.py
mDeepFRI/utils.py
mDeepFRI/alignment.py
mDeepFRI/mmseqs.py
mDeepFRI/contact_map_utils.pyx
mDeepFRI/predict.pyx
mDeepFRI/__init__.py
mDeepFRI/predict.cpython-310-x86_64-linux-gnu.so
mDeepFRI/cli.py
mDeepFRI/tests/test_utils.py
mDeepFRI/tests/test_conctact_map.py
mDeepFRI/tests/test_pdb.py
mDeepFRI/tests/test_alignment.py
mDeepFRI/tests/test_predict.py
mDeepFRI/tests/test_install.py
mDeepFRI/tests/test_bio_utils.py
mDeepFRI/tests/test_mmseqs.py
mDeepFRI/tests/__init__.py
mDeepFRI-1.1.8.dist-info/top_level.txt
mDeepFRI-1.1.8.dist-info/METADATA
mDeepFRI-1.1.8.dist-info/entry_points.txt
mDeepFRI-1.1.8.dist-info/RECORD
mDeepFRI-1.1.8.dist-info/WHEEL
mmseqs/README.md
mmseqs/userguide.pdf
mmseqs/LICENSE.md
mmseqs/bin/mmseqs
mmseqs/util/bash-completion.sh
mmseqs/matrices/PAM110.out
mmseqs/matrices/PAM150.out
mmseqs/matrices/PAM160.out
mmseqs/matrices/PAM140.out
mmseqs/matrices/blosum45.out
mmseqs/matrices/PAM100.out
mmseqs/matrices/PAM190.out
mmseqs/matrices/VTML120.out
mmseqs/matrices/blosum60.out
mmseqs/matrices/blosum80.out
mmseqs/matrices/blosum100.out
mmseqs/matrices/PAM80.out
mmseqs/matrices/PAM180.out
mmseqs/matrices/VTML80.out
mmseqs/matrices/blosum65.out
mmseqs/matrices/PAM40.out
mmseqs/matrices/blosum40.out
mmseqs/matrices/blosum85.out
mmseqs/matrices/PAM90.out
mmseqs/matrices/PAM60.out
mmseqs/matrices/VTML20.out
mmseqs/matrices/blosum90.out
mmseqs/matrices/PAM30.out
mmseqs/matrices/blosum35.out
mmseqs/matrices/blosum62.out
mmseqs/matrices/blosum30.out
mmseqs/matrices/blosum50.out
mmseqs/matrices/nucleotide.out
mmseqs/matrices/PAM70.out
mmseqs/matrices/PAM10.out
mmseqs/matrices/PAM130.out
mmseqs/matrices/blosum55.out
mmseqs/matrices/VTML10.out
mmseqs/matrices/PAM170.out
mmseqs/matrices/blosum75.out
mmseqs/matrices/PAM50.out
mmseqs/matrices/blosum95.out
mmseqs/matrices/VTML40.out
mmseqs/matrices/PAM20.out
mmseqs/matrices/VTML160.out
mmseqs/matrices/PAM120.out
mmseqs/matrices/blosum70.out
mmseqs/examples/DB.fasta
