Metadata-Version: 2.1
Name: mDeepFRI
Version: 1.1.8
Summary: Pipeline for searching and aligning contact maps for proteins, and function prediction with DeepFRI.
Home-page: https://github.com/bioinf-MCB/Metagenomic-DeepFRI
Author: Valentyn Bezshapkin
Author-email: valentyn.bezshapkin@micro.biol.ethz.ch
License: BSD-3-Clause
Project-URL: Bug Tracker, https://github.com/bioinf-mcb/Metagenomic-DeepFRI/issues
Project-URL: Changelog, https://github.com/bioinf-mcb/Metagenomic-DeepFRI/CHANGELOG.md
Project-URL: Builds, https://github.com/bioinf-mcb/Metagenomic-DeepFRI/actions
Project-URL: PyPI, https://pypi.org/project/mdeepfri
Keywords: bioinformatics,protein,function,deep-learning
Platform: any
Classifier: Programming Language :: Python :: 3
Classifier: License :: OSI Approved :: BSD License
Classifier: Operating System :: OS Independent
Classifier: Intended Audience :: Science/Research
Classifier: Topic :: Scientific/Engineering :: Bio-Informatics
Requires-Python: <3.12,>=3.9
Requires-Dist: click ~=8.0
Requires-Dist: numpy ~=1.21
Requires-Dist: biotite
Requires-Dist: pysam >=0.18
Requires-Dist: pyopal ~=0.5
Requires-Dist: foldcomp
Requires-Dist: tqdm
Requires-Dist: onnxruntime-gpu
Provides-Extra: dev
Requires-Dist: pre-commit ; extra == 'dev'
